tgalert/__init__.py
tgalert/tg_alert.py
tgalert-0.8.dist-info/DESCRIPTION.rst
tgalert-0.8.dist-info/METADATA
tgalert-0.8.dist-info/RECORD
tgalert-0.8.dist-info/WHEEL
tgalert-0.8.dist-info/metadata.json
tgalert-0.8.dist-info/top_level.txt
