Metadata-Version: 2.0
Name: tgalert
Version: 0.8
Summary: Package for receiving Telegram notifications during code execution (i.e. training).
Home-page: https://github.com/djd1283/tgalert.git
Author: David Donahue
Author-email: djd1283@gmail.com
License: UNKNOWN
Platform: UNKNOWN
Requires-Dist: python-telegram-bot
